andyreagan/__init__.py
andyreagan/main.py
andyreagan-0.2.1.dist-info/METADATA
andyreagan-0.2.1.dist-info/WHEEL
andyreagan-0.2.1.dist-info/entry_points.txt
andyreagan-0.2.1.dist-info/RECORD
