Metadata-Version: 2.4
Name: andyreagan
Version: 0.2.1
Summary: A command-line resume printer for Andy Reagan - Senior Data Scientist and educator with Ph.D. in Applied Mathematics
Author: Andy Reagan
License-Expression: MIT
Keywords: bio,cli,cv,data-science,resume
Classifier: Development Status :: 4 - Beta
Classifier: Intended Audience :: End Users/Desktop
Classifier: License :: OSI Approved :: MIT License
Classifier: Programming Language :: Python :: 3
Classifier: Programming Language :: Python :: 3.8
Classifier: Programming Language :: Python :: 3.9
Classifier: Programming Language :: Python :: 3.10
Classifier: Programming Language :: Python :: 3.11
Classifier: Programming Language :: Python :: 3.12
Classifier: Topic :: Utilities
Requires-Python: >=3.8
